src/Main.py
src/__init__.py
src/cli.py
src/config/Config.py
src/modules/__init__.py
src/modules/adapt/Adapter.py
src/modules/adapt/__init__.py
src/modules/check/Check.py
src/modules/check/__init__.py
src/modules/doc/DocGenerator.py
src/modules/doc/UrlDetector.py
src/modules/sync/Sync.py
src/modules/sync/__init__.py
src/modules/update/Updater.py
src/modules/update/__init__.py
src/resources/jumpUrl.ts
src/util/BackupManager.py
src/util/GitManager.py
src/util/GlobalRepositoryManager.py
src/util/HarmonyDetector.py
src/util/ModuleManager.py
src/util/RepositoryDetector.py
src/util/RepositoryHandler.py
src/util/SingleRepositoryHandler.py
src/util/ai/AiAgentManager.py
src/util/ai/AiMergeConfig.py
src/util/merge/CodeMerger.py
krn_harmony_adapter-1.3.10.dist-info/METADATA
krn_harmony_adapter-1.3.10.dist-info/WHEEL
krn_harmony_adapter-1.3.10.dist-info/entry_points.txt
krn_harmony_adapter-1.3.10.dist-info/top_level.txt
krn_harmony_adapter-1.3.10.dist-info/RECORD
