Metadata-Version: 2.4
Name: krn-harmony-adapter
Version: 1.3.10
Summary: KRN鸿蒙适配自动化工具
